mealy/__init__.py
mealy/constants.py
mealy/error_analysis_utils.py
mealy/error_analyzer.py
mealy/error_tree.py
mealy/error_visualizer.py
mealy/metrics.py
mealy/preprocessing.py
mealy/version.py
mealy/tests/__init__.py
mealy/tests/test_error_analyzer.py
tests/__init__.py
tests/integration/__init__.py
tests/integration/test_error_analyzer.py
tests/unit/__init__.py
tests/unit/test_error_analyzer.py
tests/unit/test_error_tree.py
tests/unit/test_error_visualizer.py
tests/unit/test_preprocessing.py
tests/unit/test_utils.py
mealy-0.2.5.dist-info/LICENSE
mealy-0.2.5.dist-info/METADATA
mealy-0.2.5.dist-info/WHEEL
mealy-0.2.5.dist-info/top_level.txt
mealy-0.2.5.dist-info/RECORD
