Metadata-Version: 2.1
Name: mealy
Version: 0.2.5
Summary: Model Error Analysis python package
Home-page: https://github.com/dataiku/mealy
Maintainer: Du Phan
Maintainer-email: du.phan@dataiku.com
License: Apache 2.0
Download-URL: https://github.com/dataiku/mealy
Platform: UNKNOWN
Classifier: Intended Audience :: Science/Research
Classifier: Intended Audience :: Developers
Classifier: Programming Language :: Python
Classifier: Topic :: Scientific/Engineering
Classifier: Operating System :: Microsoft :: Windows
Classifier: Operating System :: POSIX
Classifier: Operating System :: Unix
Classifier: Operating System :: MacOS
Classifier: Programming Language :: Python :: 3.6
Classifier: Programming Language :: Python :: 3.7
Requires-Python: >=3.6
Requires-Dist: numpy (>=1.11)
Requires-Dist: scipy (>=0.19)
Requires-Dist: kneed (==0.6.0)
Requires-Dist: scikit-learn (>=0.19)
Requires-Dist: matplotlib (>=2.0)
Requires-Dist: graphviz (>=0.14)
Provides-Extra: all
Requires-Dist: sphinx-gallery (>=0.5.0) ; extra == 'all'
Requires-Dist: sphinx (>=2.2.2) ; extra == 'all'
Provides-Extra: doc
Requires-Dist: sphinx-gallery (>=0.5.0) ; extra == 'doc'
Requires-Dist: sphinx (>=2.2.2) ; extra == 'doc'
